costock/__init__.py
costock-0.0.0.dist-info/LICENSE
costock-0.0.0.dist-info/METADATA
costock-0.0.0.dist-info/WHEEL
costock-0.0.0.dist-info/top_level.txt
costock-0.0.0.dist-info/RECORD
